gimdog-toolbox/__init__.py
gimdog-toolbox/displaying.py
gimdog-toolbox/files.py
gimdog-toolbox/inspect.py
gimdog-toolbox/metrics.py
gimdog-toolbox/preprocessing.py
gimdog-toolbox/pulseq.py
gimdog-toolbox/timing.py
gimdog_toolbox-0.1.0.dist-info/licenses/LICENSE
tests/__init__.py
tests/test_preprocessing.py
gimdog_toolbox-0.1.0.dist-info/METADATA
gimdog_toolbox-0.1.0.dist-info/WHEEL
gimdog_toolbox-0.1.0.dist-info/top_level.txt
gimdog_toolbox-0.1.0.dist-info/RECORD
