Metadata-Version: 2.4
Name: gimdog-toolbox
Version: 0.1.0
Summary: Python utility functions that I always had to rewrite
Author-email: Áron Gimesi <aron.gimesi@tecnico.ulisboa.pt>
License: CC by 4.0
Project-URL: Homepage, https://github.com/gimesia/gimdog-toolbox
Project-URL: Issues, https://github.com/gimesia/gimdog-toolbox/issues
Requires-Python: >=3.10
License-File: LICENSE
Requires-Dist: torch
Requires-Dist: numpy
Requires-Dist: opencv-python
Dynamic: license-file
